convert2ppt/__init__.py
convert2ppt/common.py
convert2ppt/config.yaml
convert2ppt/configure_llm.py
convert2ppt/convert2ppt.py
convert2ppt/extractor.py
convert2ppt/generate_json Error.py
convert2ppt/generate_json.py
convert2ppt/generate_ppt.py
convert2ppt/load_pdfs.py
convert2ppt/prompt.txt
convert2ppt-0.0.22.dist-info/LICENSE
convert2ppt-0.0.22.dist-info/METADATA
convert2ppt-0.0.22.dist-info/WHEEL
convert2ppt-0.0.22.dist-info/entry_points.txt
convert2ppt-0.0.22.dist-info/top_level.txt
convert2ppt-0.0.22.dist-info/RECORD
