Metadata-Version: 2.1
Name: convert2ppt
Version: 0.0.22
Summary: Convert your documents to PPT with AI
Author-email: Murat Karakaya <kmkarakaya@gmail.com>
License: MIT License
Project-URL: Homepage, https://github.com/kmkarakaya/convert2ppt
Keywords: convert2ppt
Classifier: Intended Audience :: Developers
Classifier: License :: OSI Approved :: MIT License
Classifier: Natural Language :: English
Classifier: Programming Language :: Python :: 3.8
Classifier: Programming Language :: Python :: 3.9
Classifier: Programming Language :: Python :: 3.10
Classifier: Programming Language :: Python :: 3.11
Classifier: Programming Language :: Python :: 3.12
Requires-Python: >=3.8
License-File: LICENSE
Requires-Dist: numpy
Requires-Dist: grpcio ==1.60.1
Requires-Dist: python-pptx
Requires-Dist: matplotlib
Requires-Dist: google-generativeai
Requires-Dist: PyMuPDF
Requires-Dist: PyYAML
Provides-Extra: all
Requires-Dist: convert2ppt[extra] ; extra == 'all'
Provides-Extra: extra
Requires-Dist: pandas ; extra == 'extra'
